samewords-0.5.3.dist-info/RECORD
samewords-0.5.3.dist-info/metadata.json
samewords-0.5.3.dist-info/WHEEL
samewords-0.5.3.dist-info/entry_points.txt
samewords-0.5.3.dist-info/DESCRIPTION.rst
samewords-0.5.3.dist-info/top_level.txt
samewords-0.5.3.dist-info/METADATA
samewords/matcher.py
samewords/__init__.py
samewords/core.py
samewords/brackets.py
samewords/cli.py
samewords/document.py
samewords/settings.py
samewords/tokenize.py
samewords/test/test_matcher.py
samewords/test/test_brackets.py
samewords/test/test_core.py
samewords/test/test_macro.py
samewords/test/__init__.py
samewords/test/test_tokenize.py
samewords/test/test_cli.py
samewords/test/test_document.py
samewords/test/assets/unicode_register.py
samewords/test/assets/__init__.py
