Metadata-Version: 2.0
Name: samewords
Version: 0.5.3
Summary: Package for disambiguation of identical terms in critical editions in LaTeX with reledmac.
Home-page: https://github.com/stenskjaer/samewords
Author: Michael Stenskjær Christensen
Author-email: michael.stenskjaer@gmail.com
License: MIT
Platform: UNKNOWN
Classifier: Development Status :: 4 - Beta
Classifier: Programming Language :: Python :: 3
Classifier: Programming Language :: Python :: 3.6
Classifier: Topic :: Text Processing :: Markup :: LaTeX
Requires-Dist: regex (==2018.8.17)
